Metadata-Version: 2.1
Name: KXMLParser
Version: 0.0.3
Summary: Rest Framework Parser xml to json
Home-page: https://github.com/k1k0borba/KXMLParser
Author: Rodrigo Borba
Author-email: k1k0borba@gmail.com
License: MIT License
Keywords: Xml2Json,XMLParser
Platform: UNKNOWN
